{
  "_class": "shapePath",
  "booleanOperation": -1,
  "clippingMaskMode": 0,
  "do_objectID": "1F929C7C-EBF9-42A2-9503-47889A3CF288",
  "edited": true,
  "exportOptions": {
    "_class": "exportOptions",
    "exportFormats": [
    ],
    "includedLayerIds": [
    ],
    "layerOptions": 0,
    "shouldTrim": false
  },
  "frame": {
    "_class": "rect",
    "constrainProportions": false,
    "height": 0.6089664376451971,
    "width": 0.6567478951444147,
    "x": 0.819644220365885,
    "y": 2.291093426479719
  },
  "hasClippingMask": false,
  "isClosed": true,
  "isFixedToViewport": false,
  "isFlippedHorizontal": false,
  "isFlippedVertical": false,
  "isLocked": false,
  "isTemplate": false,
  "isVisible": true,
  "layerListExpandedType": 0,
  "name": "Path",
  "nameIsFixed": false,
  "pointRadiusBehaviour": 1,
  "points": [
    {
      "_class": "curvePoint",
      "cornerRadius": 0,
      "cornerStyle": 0,
      "curveFrom": "{0.86837263756481353, 0.015873015873019942}",
      "curveMode": 4,
      "curveTo": "{1, 0.039862914862915641}",
      "hasCurveFrom": true,
      "hasCurveTo": false,
      "point": "{1, 0.039862914862915641}"
    },
    {
      "_class": "curvePoint",
      "cornerRadius": 0,
      "cornerStyle": 0,
      "curveFrom": "{0.21859842783073472, 0}",
      "curveMode": 3,
      "curveTo": "{0.71516976082957373, 0}",
      "hasCurveFrom": true,
      "hasCurveTo": true,
      "point": "{0.56899147014550855, 0}"
    },
    {
      "_class": "curvePoint",
      "cornerRadius": 0,
      "cornerStyle": 0,
      "curveFrom": "{0, 0.85064935064935476}",
      "curveMode": 2,
      "curveTo": "{0, 0.15007215007214939}",
      "hasCurveFrom": true,
      "hasCurveTo": true,
      "point": "{0, 0.4960317460317476}"
    },
    {
      "_class": "curvePoint",
      "cornerRadius": 0,
      "cornerStyle": 0,
      "curveFrom": "{0.68590065228299202, 1}",
      "curveMode": 3,
      "curveTo": "{0.2042147516307086, 1}",
      "hasCurveFrom": true,
      "hasCurveTo": true,
      "point": "{0.48904499080113489, 1}"
    },
    {
      "_class": "curvePoint",
      "cornerRadius": 0,
      "cornerStyle": 0,
      "curveFrom": "{1, 0.77164502164502768}",
      "curveMode": 4,
      "curveTo": "{0.86118079946479575, 0.89826839826840432}",
      "hasCurveFrom": false,
      "hasCurveTo": true,
      "point": "{1, 0.77164502164502768}"
    }
  ],
  "resizingConstraint": 63,
  "resizingType": 0,
  "rotation": 0,
  "shouldBreakMaskChain": false,
  "style": {
    "_class": "style",
    "blur": {
      "_class": "blur",
      "center": "{0.5, 0.5}",
      "isEnabled": false,
      "motionAngle": 0,
      "radius": 10,
      "saturation": 1,
      "type": 0
    },
    "borderOptions": {
      "_class": "borderOptions",
      "dashPattern": [
      ],
      "isEnabled": true,
      "lineCapStyle": 0,
      "lineJoinStyle": 0
    },
    "borders": [
    ],
    "colorControls": {
      "_class": "colorControls",
      "brightness": 0,
      "contrast": 1,
      "hue": 0,
      "isEnabled": false,
      "saturation": 1
    },
    "contextSettings": {
      "_class": "graphicsContextSettings",
      "blendMode": 0,
      "opacity": 1
    },
    "do_objectID": "60D74441-1BAD-44C4-823E-64B3FA2AC0FE",
    "endMarkerType": 0,
    "fills": [
    ],
    "innerShadows": [
    ],
    "miterLimit": 10,
    "shadows": [
    ],
    "startMarkerType": 0,
    "windingRule": 1
  }
}