{
  "_class": "shapePath",
  "booleanOperation": -1,
  "clippingMaskMode": 0,
  "do_objectID": "FF8027D8-9D9E-477B-9763-2F43A1A92B3B",
  "edited": true,
  "exportOptions": {
    "_class": "exportOptions",
    "exportFormats": [
    ],
    "includedLayerIds": [
    ],
    "layerOptions": 0,
    "shouldTrim": false
  },
  "frame": {
    "_class": "rect",
    "constrainProportions": false,
    "height": 8.054733727810653,
    "width": 5.407645709369849,
    "x": 8.144849093124957,
    "y": 5.924556213017753
  },
  "hasClippingMask": false,
  "isClosed": true,
  "isFixedToViewport": false,
  "isFlippedHorizontal": false,
  "isFlippedVertical": false,
  "isLocked": false,
  "isVisible": true,
  "layerListExpandedType": 0,
  "name": "Shape-path",
  "nameIsFixed": false,
  "pointRadiusBehaviour": 1,
  "points": [
    {
      "_class": "curvePoint",
      "cornerRadius": 0,
      "cornerStyle": 0,
      "curveFrom": "{1, 1}",
      "curveMode": 1,
      "curveTo": "{1, 1}",
      "hasCurveFrom": false,
      "hasCurveTo": false,
      "point": "{1, 1}"
    },
    {
      "_class": "curvePoint",
      "cornerRadius": 0,
      "cornerStyle": 0,
      "curveFrom": "{0, 1}",
      "curveMode": 1,
      "curveTo": "{0, 1}",
      "hasCurveFrom": false,
      "hasCurveTo": false,
      "point": "{0, 1}"
    },
    {
      "_class": "curvePoint",
      "cornerRadius": 0,
      "cornerStyle": 0,
      "curveFrom": "{0.41975308641975284, 0.17355371900826444}",
      "curveMode": 4,
      "curveTo": "{0.38271604938271614, 0.256198347107438}",
      "hasCurveFrom": true,
      "hasCurveTo": false,
      "point": "{0.38271604938271614, 0.256198347107438}"
    },
    {
      "_class": "curvePoint",
      "cornerRadius": 0,
      "cornerStyle": 0,
      "curveFrom": "{0.53086419753086378, 0.082644628099173556}",
      "curveMode": 4,
      "curveTo": "{0.45679012345678954, 0.082644628099173556}",
      "hasCurveFrom": true,
      "hasCurveTo": true,
      "point": "{0.49382716049382708, 0}"
    },
    {
      "_class": "curvePoint",
      "cornerRadius": 0,
      "cornerStyle": 0,
      "curveFrom": "{0.61728395061728381, 0.26446280991735549}",
      "curveMode": 4,
      "curveTo": "{0.56790123456790131, 0.17355371900826444}",
      "hasCurveFrom": false,
      "hasCurveTo": true,
      "point": "{0.61728395061728381, 0.26446280991735549}"
    }
  ],
  "resizingConstraint": 63,
  "resizingType": 0,
  "rotation": 0,
  "shouldBreakMaskChain": false,
  "style": {
    "_class": "style",
    "blur": {
      "_class": "blur",
      "center": "{0.5, 0.5}",
      "isEnabled": false,
      "motionAngle": 0,
      "radius": 10,
      "saturation": 1,
      "type": 0
    },
    "borderOptions": {
      "_class": "borderOptions",
      "dashPattern": [
      ],
      "isEnabled": true,
      "lineCapStyle": 0,
      "lineJoinStyle": 0
    },
    "borders": [
    ],
    "colorControls": {
      "_class": "colorControls",
      "brightness": 0,
      "contrast": 1,
      "hue": 0,
      "isEnabled": false,
      "saturation": 1
    },
    "contextSettings": {
      "_class": "graphicsContextSettings",
      "blendMode": 0,
      "opacity": 1
    },
    "do_objectID": "51927533-F49F-41E0-BA91-BA6346BB34CB",
    "endMarkerType": 0,
    "fills": [
    ],
    "innerShadows": [
    ],
    "miterLimit": 10,
    "shadows": [
    ],
    "startMarkerType": 0,
    "windingRule": 1
  }
}