{
  "_class": "group",
  "booleanOperation": -1,
  "clippingMaskMode": 0,
  "do_objectID": "F10B0D2F-81E9-4608-B560-ACA6E28B174D",
  "exportOptions": {
    "_class": "exportOptions",
    "exportFormats": [
    ],
    "includedLayerIds": [
    ],
    "layerOptions": 0,
    "shouldTrim": false
  },
  "frame": {
    "_class": "rect",
    "constrainProportions": false,
    "height": 95,
    "width": 1440,
    "x": 240,
    "y": 509
  },
  "groupLayout": {
    "_class": "MSImmutableFreeformGroupLayout"
  },
  "hasClickThrough": false,
  "hasClippingMask": false,
  "isFixedToViewport": false,
  "isFlippedHorizontal": false,
  "isFlippedVertical": false,
  "isLocked": false,
  "isTemplate": false,
  "isVisible": true,
  "layerListExpandedType": 2,
  "layers": [
    {
      "class": "rectangle",
      "id": "46415A6A-EAA7-4A9F-B41F-ED208E10D0CD"
    },
    {
      "class": "symbolInstance",
      "id": "277A41E6-FAE5-4338-9531-D73B94BD5E9A"
    },
    {
      "class": "rectangle",
      "id": "3566C773-F7DE-48FE-9664-1FD8D7D61EEE"
    },
    {
      "class": "text",
      "id": "0D98502B-D015-4FAA-B78F-AF16DCB06962"
    },
    {
      "class": "text",
      "id": "332E057D-1AAC-4325-9F95-9153EE5AA7C1"
    },
    {
      "class": "text",
      "id": "3FE1B985-FF3A-42C8-9C1E-77F8935332ED"
    },
    {
      "class": "text",
      "id": "EAF6B4CF-9EF6-4AB6-9FCF-69AE551D533C"
    }
  ],
  "name": "shipping-line",
  "nameIsFixed": true,
  "resizingConstraint": 63,
  "resizingType": 0,
  "rotation": 0,
  "shouldBreakMaskChain": false,
  "style": {
    "_class": "style",
    "blur": {
      "_class": "blur",
      "center": "{0.5, 0.5}",
      "isEnabled": false,
      "motionAngle": 0,
      "radius": 10,
      "saturation": 1,
      "type": 0
    },
    "borderOptions": {
      "_class": "borderOptions",
      "dashPattern": [
      ],
      "isEnabled": true,
      "lineCapStyle": 0,
      "lineJoinStyle": 0
    },
    "borders": [
    ],
    "colorControls": {
      "_class": "colorControls",
      "brightness": 0,
      "contrast": 1,
      "hue": 0,
      "isEnabled": false,
      "saturation": 1
    },
    "contextSettings": {
      "_class": "graphicsContextSettings",
      "blendMode": 0,
      "opacity": 1
    },
    "do_objectID": "3EAFBB6C-7304-40B7-ACF5-D42E972A266B",
    "endMarkerType": 0,
    "fills": [
    ],
    "innerShadows": [
    ],
    "miterLimit": 10,
    "shadows": [
    ],
    "startMarkerType": 0,
    "windingRule": 1
  }
}